fastapi_react_admin/__init__.py
fastapi_react_admin/react_admin.py
fastapi_react_admin/schemas.py
fastapi_react_admin-2.1.1.dist-info/METADATA
fastapi_react_admin-2.1.1.dist-info/WHEEL
fastapi_react_admin-2.1.1.dist-info/RECORD
