Metadata-Version: 2.1
Name: fastapi-react-admin
Version: 2.1.1
Summary: Module to automaticly generate fastapi routes for using react admin
Author: Enveloss
Requires-Python: >=3.9,<4.0
Classifier: Programming Language :: Python :: 3
Classifier: Programming Language :: Python :: 3.9
Classifier: Programming Language :: Python :: 3.10
Classifier: Programming Language :: Python :: 3.11
Requires-Dist: fastapi (>=0.95,<0.96)
Requires-Dist: sqlalchemy (>=2.0,<2.1)
